wcounts/__init__.py
wcounts/plotting.py
wcounts/wcounts.py
wcounts-0.1.0.dist-info/LICENSE
wcounts-0.1.0.dist-info/WHEEL
wcounts-0.1.0.dist-info/METADATA
wcounts-0.1.0.dist-info/RECORD
